folder_sync/__init__.py
folder_sync/main.py
folder_sync/utils.py
folder_sync_cli-1.1.9.dist-info/LICENSE
folder_sync_cli-1.1.9.dist-info/METADATA
folder_sync_cli-1.1.9.dist-info/WHEEL
folder_sync_cli-1.1.9.dist-info/entry_points.txt
folder_sync_cli-1.1.9.dist-info/top_level.txt
folder_sync_cli-1.1.9.dist-info/RECORD
