Metadata-Version: 2.1
Name: folder-sync-cli
Version: 1.1.9
Summary: A CLI tool to simplify rclone sync.
Home-page: https://github.com/hank-chouu/folder-sync-cli
Author: Heng-Tse Chou
Author-email: hengtse.me@gmail.com
License: MIT
Keywords: rclone CLI
Classifier: Development Status :: 3 - Alpha
Classifier: Intended Audience :: End Users/Desktop
Classifier: Operating System :: Unix
Classifier: Programming Language :: Python :: 3
License-File: LICENSE
Requires-Dist: click
